feincms_simplegallery/__init__.py
feincms_simplegallery/admin.py
feincms_simplegallery/apps.py
feincms_simplegallery/models.py
feincms_simplegallery/tests.py
feincms_simplegallery/views.py
feincms_simplegallery/content_types/__init__.py
feincms_simplegallery/content_types/base_gallery.py
feincms_simplegallery/content_types/slider.py
feincms_simplegallery/locale/ru/LC_MESSAGES/django.mo
feincms_simplegallery/locale/ru/LC_MESSAGES/django.po
feincms_simplegallery/templates/content/simplegallery/gallery/grid/container.html
feincms_simplegallery/templates/content/simplegallery/gallery/lightbox/container.html
feincms_simplegallery/templates/content/simplegallery/gallery/lightbox/element.html
feincms_simplegallery/templates/content/simplegallery/gallery/slider/container.html
feincms_simplegallery/templates/content/simplegallery/slider/container.html
feincms_simplegallery/util/__init__.py
feincms_simplegallery/util/base.py
feincms_simplegallery/util/mixins.py
feincms_simplegallery-0.3.1.dist-info/LICENSE
feincms_simplegallery-0.3.1.dist-info/METADATA
feincms_simplegallery-0.3.1.dist-info/WHEEL
feincms_simplegallery-0.3.1.dist-info/top_level.txt
feincms_simplegallery-0.3.1.dist-info/RECORD
